{
  "4bf58ec": "Sales",
  "7b9d3b70": "Long term",
  "3b77cb8f": " reNTALS",
  "1ba1d90": "sHORT TERM",
  "68154f8f": " RENTALS",
  "400bf34": "FREE ",
  "13ede05": "Resources",
  "-5129f828": "Tamraght Homes",
  "b099318": "Where you live Matters",
  "6b68544c": "Properties for rent & Sale in Souss-Masaa",
  "4b050ec": "SALES",
  "-238f84e1": "Long Term Rentals",
  "-5b5b66c1": "SHORT TERM RENTALS",
  "-10c5d57b": "LAND & NEW HOMES",
  "-70d4fbaf": "ABOUT Us",
  "269d713f": "AREAS WE COVER",
  "43babb44": "TAMRAGHT HOUSES FOR SALE & RENT",
  "-446fbf84": "Abdulfattah",
  "-7eec8298": "Typically replies in a few hours",
  "3302605c": "AbDulfattah",
  "-2e666e8c": "How may I be of assistance? 😊",
  "-21c3aa38": "Start Whatsapp Chat",
  "27808a0f": "About US ",
  "200d": "‍",
  "-56dfecc9": "Abdulfattah has over twenty years of experience in estate agency. He is fluent in darija, french and English. Abdulfattah has an in depth knowledge of the area of Souss Massa and his speciality is sourcing property for clients that are not openly for sale. TEll him what you want and he will find it!",
  "-733d60e1": "Harriet",
  "6be10fb9": "Harriet is a former lettings Agent and interior designer from the united Kingdom. She provides Abdulfattah with auxillary support as well as helping clients furnish their new homes.. ",
  "-503226a1": "Areas We Cover",
  "7c12004d": "Illustration by Shannon LUnd",
  "-75ff9d31": "We provide our services from Agadir  to IMI Ouaddar, however if we feel we can add value we source properties for clients further afield, if you feel this is you please don't hesitate to contact us.",
  "7f2746be": "Contact US",
  "9df13d4": " Please don't hesitate to contact us...",
  "24eeab": "Name",
  "-2b7010d0": "Email Address",
  "-63dc6819": "Message",
  "5a0ea5a1": "Thank you! Your submission has been received!",
  "-7c112e99": "Oops! Something went wrong while submitting the form.",
  "-2d5ad901": "Long term Rentals",
  "94bbff5": "Properties for Sale ",
  "3b180342": "See More",
  "-1c93fc36": " Have Questions? Can't find what you're looking for?",
  "3d503d2b": "No items found.",
  "4a01f95f": "Short Term Rentals",
  "-6d602539": "Land & New Homes for Sale ",
  "49a057c4": "Page not found",
  "c938": "404",
  "583f3656": "The page you are looking for doesn't exist or has been moved.",
  "66ef27a": "Back to Homepage",
  "-1d907d94": "Our Guide to life in Morocco",
  "4ef7574e": "Find out more"
}